{
  "balances": {
    "1057200241104912466": 90028,
    "1075964775504285696": 4575,
    "785896336583163925": 39701,
    "1043956095519035493": 78140,
    "944667721826705489": 8100,
    "584812997776637963": 395,
    "808828916432633876": 5000,
    "706949972985118731": 24750,
    "977024037660278796": 58010,
    "775420795861205013": 18701,
    "1126613271445782579": -203,
    "1067637524786331658": 1786,
    "1058983440252416040": 300
  },
  "shop": {
    "sendWiiMessage": {},
    "spotifyRequest": {}
  },
  "bug reports": {},
  "tickets": {},
  "stocks": {
    "PCB": {
      "display": "ProCraftBot",
      "value": -81,
      "previous": 19,
      "updateTime": "2023-11-06T02:03:35.618Z",
      "owners": {
        "775420795861205013": {
          "purchaseCost": 64.35000000000001,
          "amount": 101
        },
        "785896336583163925": {
          "purchaseCost": 118.8,
          "amount": 5
        },
        "584812997776637963": {
          "purchaseCost": 19.8,
          "amount": 10
        }
      }
    },
    "PCD": {
      "display": "ProCraftDiscord",
      "value": 764,
      "previous": 695,
      "updateTime": "2023-11-04T02:03:39.565Z",
      "owners": {
        "1126613271445782579": {
          "purchaseCost": 662.8875,
          "amount": 17
        },
        "1067637524786331658": {
          "purchaseCost": 632.5,
          "amount": 2
        },
        "584812997776637963": {
          "purchaseCost": 695.2,
          "amount": 15
        }
      }
    },
    "STRM": {
      "display": "Stream",
      "value": 381,
      "previous": 331,
      "updateTime": "2023-11-04T00:04:57.060Z",
      "owners": {
        "1057200241104912466": {
          "purchaseCost": 121,
          "amount": 2
        },
        "775420795861205013": {
          "purchaseCost": 139.7,
          "amount": 8
        }
      }
    },
    "channelId": "1161785056675758090",
    "messageId": "1161785784525930496"
  }
}